[
    {
        "title": "Video 1",
        "url": "y2mate.com - CocaCola  4K Commercial  Product Video_1080p.mp4",
        "website": "website",
        "category": "Product Advertising",
        "likes": 0,
        "views": 0,
        "WatchHours" : 0,
        "videoId" : "qwert3",
        "thumbnail" : "thumbnail.jpeg"
    },
    {
        "title": "Video 2",
        "url": "y2mate.com - Words That Work  Communicate Clearly With Grammarly_1080p.mp4",
        "website": "website",
        "category": "Brand Advertising",
        "likes": 0,
        "views": 0,
        "WatchHours" : 0,
        "videoId" : "asd2",
        "thumbnail" : "thumbnail.jpeg"
    },
    {
        "title": "Video 3",
        "url": "y2mate.com - CocaCola  4K Commercial  Product Video_1080p.mp4",
        "website": "website",
        "category": "Corporate Advertising",
        "likes": 0,
        "views": 0,
        "WatchHours" : 0,
        "videoId" : "qw23e",
        "thumbnail" : "thumbnail.jpeg"
    },
    {
        "title": "Video 4",
        "url": "y2mate.com - Words That Work  Communicate Clearly With Grammarly_1080p.mp4",
        "website": "website",
        "category": "Public Service Advertising (PSA)",
        "likes": 0,
        "views": 0,
        "WatchHours" : 0,
        "videoId" : "zaq2",
        "thumbnail" : "thumbnail.jpeg"
    },
    {
        "title": "Video 5",
        "url": "y2mate.com - CocaCola  4K Commercial  Product Video_1080p.mp4",
        "website": "website",
        "category": "Retail Advertising",
        "likes": 0,
        "views": 0,
        "WatchHours" : 0,
        "videoId" : "aqwert",
        "thumbnail" : "thumbnail.jpeg"
    },
    {
        "title": "Video 6",
        "url": "y2mate.com - New Coca Cola Stable Diffusion AI Ad_480p.mp4",
        "website": "website",
        "category": "B2B Advertising",
        "likes": 0,
        "views": 0,
        "WatchHours" : 0,
        "videoId" : "qwert2",
        "thumbnail" : "thumbnail.jpeg"
    },
    {
        "title": "Video 7",
        "url": "y2mate.com - New Coca Cola Stable Diffusion AI Ad_480p.mp4",
        "website": "website",
        "category": "Celebrity Endorsements",
        "likes": 0,
        "views": 0,
        "videoId" : "asdwer",
        "thumbnail"  : "thumbnail.jpeg"
    },
    {
        "title": "Video 8",
        "url": "y2mate.com - New Coca Cola Stable Diffusion AI Ad_480p.mp4",
        "website": "website",
        "category": "Event Sponsorship",
        "likes": 0,
        "views": 0,
        "videoId" : "aqwerr",
        "thumbnail" : "thumbnail.jpeg"
    },
    {
        "title": "Video 9",
        "url": "vidone.mp4",
        "website": "website",
        "category": "Corporate Advertising",
        "likes": 0,
        "views": 0,
        "WatchHours" : 0,
        "videoId" : "uiouryiter",
        "thumbnail" : "thumbnail.jpeg"
    },
    {
        "title": "Video 10",
        "url": "y2mate.com - CocaCola  4K Commercial  Product Video_1080p.mp4",
        "website": "website",
        "category": "Product Advertising",
        "likes": 0,
        "views": 0,
        "videoId" : "sfrgthyj",
        "thumbnail" : "thumbnail.jpeg"
    },
    {
        "title": "Video 11",
        "url": "y2mate.com - New Coca Cola Stable Diffusion AI Ad_480p.mp4",
        "website": "website",
        "category": "Brand Advertising",
        "likes": 0,
        "views": 0,
        "WatchHours" : 0,
        "videoId" : "egtyjuiryyr",
        "thumbnail" : "thumbnail.jpeg"
    },
    {
        "title": "Video 12",
        "url": "y2mate.com - Fanta  Product Commercial_1080pFHR.mp4",
        "website": "website",
        "category": "Corporate Advertising",
        "likes": 0,
        "views": 0,
        "WatchHours" : 0,
        "videoId" : "dfhfjukuilui",
        "thumbnail" : "thumbnail.jpeg"
    },
    {
        "title": "Video 13",
        "url": "vidfive.mp4",
        "website": "website",
        "category": "Corporate Advertising",
        "likes": 0,
        "views": 0,
        "WatchHours" : 0,
        "videoId" : "qwert13",
        "thumbnail" : "thumbnail.jpeg"
    },
    {
        "title": "Video 14",
        "url": "vidone.mp4",
        "website": "website",
        "category": "Brand Advertising",
        "likes": 0,
        "views": 0,
        "WatchHours" : 0,
        "videoId" : "qwert14",
        "thumbnail" : "thumbnail.jpeg"
    },
    {
        "title": "Video 15",
        "url": "vidtwo.mp4",
        "website": "website",
        "category": "Corporate Advertising",
        "likes": 0,
        "views": 0,
        "WatchHours" : 0,
        "videoId" : "qwerty15",
        "thumbnail" : "thumbnail.jpeg"
    },
    {
        "title": "Video 16",
        "url": "All the Best Moments are Better With Pepsi.mp4",
        "website": "website",
        "category": "Product Advertising",
        "likes": 0,
        "views": 0,
        "WatchHours" : 0,
        "videoId" : "qwerty16",
        "thumbnail" : "thumbnail.jpeg"
    },
    {
        "title": "Video 17",
        "url": "BMW M4 - _Ultimate Racetrack_.mp4",
        "website": "website",
        "category": "Brand Advertising",
        "likes": 0,
        "views": 0,
        "WatchHours" : 0,
        "videoId" : "qwerty17",
        "thumbnail" : "thumbnail.jpeg"
    },
    {
        "title": "Video 18",
        "url": "BUGATTI CHIRON Pur Sport_ ‘C’ the Drift.mp4",
        "website": "website",
        "category": "Brand Advertising",
        "likes": 0,
        "views": 0,
        "WatchHours" : 0,
        "videoId" : "qwert18",
        "thumbnail" : "thumbnail.jpeg"
    },
    {
        "title": "Video 19",
        "url": "CITIZEN TV 3D INTRO ANIMATION (REMAKE).mp4",
        "website": "website",
        "category": "Corporate Advertising",
        "likes": 0,
        "views": 0,
        "WatchHours" : 0,
        "videoId" : "qwert19",
        "thumbnail"  : "thumbnail.jpeg"
    },
    {
        "title": "Video 20",
        "url": "Dancing Babys  - Evian Commercial _ 2013 _The New Funny Evian Commercial.mp4",
        "website": "website",
        "category": "Event Sponsorship",
        "likes": 0,
        "views": 0,
        "WatchHours" : 0,
        "videoId" : "qwert20",
        "thumbnail" : "thumbnail.jpeg"
    },
    {
        "title": "Video 21",
        "url": "vidthree.mp4",
        "website": "website",
        "category": "Corporate Advertising",
        "likes": 0,
        "views": 0,
        "WatchHours" : 0,
        "videoId" : "qwerty21",
        "thumbnail" : "thumbnail.jpeg"
    },
    {
        "title": "Video 22",
        "url": "vidseven.mp4",
        "website": "website",
        "category": "Product Advertising",
        "likes": 0,
        "views": 0,
        "WatchHours": "",
        "videoId" : "qwert22",
        "thumbnail" : "thumbnail.jpeg"
    },
    {
        "title": "Video 23",
        "url": "vidtwo.mp4",
        "website": "website",
        "category": "Brand Advertising",
        "likes": 0,
        "views": 0,
        "WatchHours" : 0,
        "videoId" : "qwert23",
        "thumbnail" : "thumbnail.jpeg"
    },
    {
        "title": "Video 24",
        "url": "McDonalds FUNNY AD.mp4",
        "website": "website",
        "category": "Brand Advertising",
        "likes": 0,
        "views": 0,
        "WatchHours" : 0,
        "videoId" : "qwert24",
        "thumbnail" : "thumbnail.jpeg"
    },
    {
        "title": "Video 25",
        "url": "The Beekeeper _ Official Trailer _ Starring Jason Statham.mp4",
        "website": "website",
        "category": "Product Advertising",
        "likes": 0,
        "views": 0,
        "WatchHours" : 0,
        "videoId" : "qwert25",
        "thumbnail" : "thumbnail.jpeg"
    },
    {
        "title": "Video 26",
        "url": "vidsix.mp4",
        "website": "website",
        "category": "Brand Advertising",
        "likes": 0,
        "views": 0,
        "WatchHours" : 0,
        "videoId" : "qwert26",
        "thumbnail" : "thumbnail.jpeg"
    },
    {
        "title": "Video 27",
        "url": "Betika  Pata More na Free Bets.mp4",
        "website": "website",
        "category": "Product Advertising",
        "likes": 0,
        "views": 0,
        "WatchHours" : 0,
        "videoId" : "ad20204v1",
        "thumbnail" : "thumbnail.jpeg"
    },
    {
        "title": "Video 28",
        "url": " Citizen News App for Android.mp4",
        "website": "website",
        "category": "Brand Advertising",
        "likes": 0,
        "views": 0,
        "WatchHours" : 0,
        "videoId" : "ad2024v2",
        "thumbnail" : "thumbnail.jpeg"
    },
    {
        "title": "Video 29",
        "url": "y2mate.com - Naivas Kikapu Kibonge_1080p.mp4",
        "website": "website",
        "category": "Corporate Advertising",
        "likes": 0,
        "views": 0,
        "WatchHours" : 0,
        "videoId" : "ad2024v3",
        "thumbnail" : "thumbnail.jpeg"
    },
    {
        "title": "Video 30",
        "url": "TUSKER US  Latest TV Commercial_1080p.mp4",
        "website": "website",
        "category": "Public Service Advertising (PSA)",
        "likes": 0,
        "views": 0,
        "WatchHours" : 0,
        "videoId" : "ad2024v4",
        "thumbnail" : "thumbnail.jpeg"
    },
    {
        "title": "Video 31",
        "url": " TASTE THE 2IN1 CHOCO GOODNESS BBCHOCO.mp4",
        "website": "website",
        "category": "Retail Advertising",
        "likes": 0,
        "views": 0,
        "WatchHours" : 0,
        "videoId" : "ad2024v5",
        "thumbnail" : "thumbnail.jpeg"
    },
    {
        "title": "Video 32",
        "url": "Zidisha Ladha Na Blue Band.mp4",
        "website": "website",
        "category": "B2B Advertising",
        "likes": 0,
        "views": 0,
        "WatchHours" : 0,
        "videoId" : "ad2024v6",
        "thumbnail" : "thumbnail.jpeg"
    },
    {
        "title": "Video 33",
        "url": "Blue Band Peanut Butter.mp4",
        "website": "website",
        "category": "Celebrity Endorsements",
        "likes": 0,
        "views": 0,
        "videoId" : "ad2024v7",
        "thumbnail"  : "thumbnail.jpeg"
    },
    {
        "title": "Video 34",
        "url": "y2mate.com - September 2022 Intake advert_1080p.mp4",
        "website": "website",
        "category": "Event Sponsorship",
        "likes": 0,
        "views": 0,
        "videoId" : "ad2024v8",
        "thumbnail" : "thumbnail.jpeg"
    },
    {
        "title": "Video 35",
        "url": "y2mate.com - CallBilaWorries for as low as 150 bob to all networks_1080p.mp4",
        "website": "website",
        "category": "Corporate Advertising",
        "likes": 0,
        "views": 0,
        "WatchHours" : 0,
        "videoId" : "ad2024v9",
        "thumbnail" : "thumbnail.jpeg"
    },
    {
        "title": "Video 36",
        "url": "y2mate.com - Safaricom ET  Internet is Life_1080p.mp4",
        "website": "website",
        "category": "Product Advertising",
        "likes": 0,
        "views": 0,
        "videoId" : "ad2024v10",
        "thumbnail" : "thumbnail.jpeg"
    },
    {
        "title": "Video 37",
        "url": "y2mate.com - Brookside DairyBest Kenyas first language_1080p.mp4",
        "website": "website",
        "category": "Brand Advertising",
        "likes": 0,
        "views": 0,
        "WatchHours" : 0,
        "videoId" : "ad2024v11",
        "thumbnail" : "thumbnail.jpeg"
    },
    {
        "title": "Video 38",
        "url": "y2mate.com - DIARY GOLD FULL CREAM MILK  ITS DAIRRYCIOUS_1080p.mp4",
        "website": "website",
        "category": "Corporate Advertising",
        "likes": 0,
        "views": 0,
        "WatchHours" : 0,
        "videoId" : "ad2024v12",
        "thumbnail" : "thumbnail.jpeg"
    },
    {
        "title": "Video 39",
        "url": "y2mate.com - Mount Kenya Milk_1080p.mp4",
        "website": "website",
        "category": "Corporate Advertising",
        "likes": 0,
        "views": 0,
        "WatchHours" : 0,
        "videoId" : "ad2024v13",
        "thumbnail" : "thumbnail.jpeg"
    },
    {
        "title": "Video 40",
        "url": "y2mate.com - Summit Lageravi_480p.mp4",
        "website": "website",
        "category": "Brand Advertising",
        "likes": 0,
        "views": 0,
        "WatchHours" : 0,
        "videoId" : "ad2024v14",
        "thumbnail" : "thumbnail.jpeg"
    },
    {
        "title": "Video 41",
        "url": "y2mate.com - Johnnie Walker  Keep Walking_1080p.mp4",
        "website": "website",
        "category": "Corporate Advertising",
        "likes": 0,
        "views": 0,
        "WatchHours" : 0,
        "videoId" : "ad2024v15",
        "thumbnail" : "thumbnail.jpeg"
    },
    {
        "title": "Video 42",
        "url": "y2mate.com - tusker beer can product visualization_1080p.mp4",
        "website": "website",
        "category": "Product Advertising",
        "likes": 0,
        "views": 0,
        "WatchHours" : 0,
        "videoId" : "ad2024v16",
        "thumbnail" : "thumbnail.jpeg"
    },
    {
        "title": "Video 43",
        "url": "y2mate.com - WE LIVE FOR TASTE TVC TUSKER CIDER KENYA_1080p.mp4",
        "website": "website",
        "category": "Brand Advertising",
        "likes": 0,
        "views": 0,
        "WatchHours" : 0,
        "videoId" : "ad2024v17",
        "thumbnail" : "thumbnail.jpeg"
    },
    {
        "title": "Video 44",
        "url": "y2mate.com - Charger Charger All the time kwani what is it  UnlimiNET_1080p.mp4",
        "website": "website",
        "category": "Brand Advertising",
        "likes": 0,
        "views": 0,
        "WatchHours" : 0,
        "videoId" : "ad2024v18",
        "thumbnail" : "thumbnail.jpeg"
    },
    {
        "title": "Video 45",
        "url": "y2mate.com - Sprite Heat Happens Stay Cool  Grocery Fail_1080p.mp4",
        "website": "website",
        "category": "Corporate Advertising",
        "likes": 0,
        "views": 0,
        "WatchHours" : 0,
        "videoId" : "ad2024v19",
        "thumbnail"  : "thumbnail.jpeg"
    },
    {
        "title": "Video 46",
        "url": "y2mate.com - THE BAHATIS OFFICIAL TV AD  RAHA PREMIUM_1080p.mp4",
        "website": "website",
        "category": "Event Sponsorship",
        "likes": 0,
        "views": 0,
        "WatchHours" : 0,
        "videoId" : "ad2024v20",
        "thumbnail" : "thumbnail.jpeg"
    },
    {
        "title": "Video 47",
        "url": "y2mate.com - Tunza Mali Yako_1080p.mp4",
        "website": "website",
        "category": "Corporate Advertising",
        "likes": 0,
        "views": 0,
        "WatchHours" : 0,
        "videoId" : "ad2024v21",
        "thumbnail" : "thumbnail.jpeg"
    },
    {
        "title": "Video 48",
        "url": "y2mate.com - ILARA Mawowowo   MyILARAFamily_480p.mp4",
        "website": "website",
        "category": "Product Advertising",
        "likes": 0,
        "views": 0,
        "WatchHours": "",
        "videoId" : "ad2024v22",
        "thumbnail" : "thumbnail.jpeg"
    },
    {
        "title": "Video 49",
        "url": "y2mate.com - Chuma mzito  Doshi Steel.mp4",
        "website": "website",
        "category": "Brand Advertising",
        "likes": 0,
        "views": 0,
        "WatchHours" : 0,
        "videoId" : "ad2024v23",
        "thumbnail" : "thumbnail.jpeg"
    },
    {
        "title": "Video 50",
        "url": "y2mate.com - The Equity Anthem.mp4",
        "website": "website",
        "category": "Brand Advertising",
        "likes": 0,
        "views": 0,
        "WatchHours" : 0,
        "videoId" : "ad2024v24",
        "thumbnail" : "thumbnail.jpeg"
    },
    {
        "title": "Video 51",
        "url": "y2mate.com - KCB MPESA  Borrow a KCB MPESA loan today Simply go to your MPESA App.mp4",
        "website": "website",
        "category": "Product Advertising",
        "likes": 0,
        "views": 0,
        "WatchHours" : 0,
        "videoId" : "ad2024v25",
        "thumbnail" : "thumbnail.jpeg"
    },
    {
        "title": "Video 52",
        "url": "y2mate.com - KCB Ni Yetu  For People For Better_1080p.mp4",
        "website": "website",
        "category": "Brand Advertising",
        "likes": 0,
        "views": 0,
        "WatchHours" : 0,
        "videoId" : "ad2024v26",
        "thumbnail" : "thumbnail.jpeg"
    },
    {
        "title": "Video 53",
        "url": "y2mate.com - KCB CUB ACCOUNT  ANIMATION_720p.mp4",
        "website": "website",
        "category": "Product Advertising",
        "likes": 0,
        "views": 0,
        "WatchHours" : 0,
        "videoId" : "ad2024v27",
        "thumbnail" : "thumbnail.jpeg"
    },
    {
        "title": "Video 54",
        "url": "y2mate.com - NHIF ADVERT 2021_480p.mp4",
        "website": "website",
        "category": "Brand Advertising",
        "likes": 0,
        "views": 0,
        "WatchHours" : 0,
        "videoId" : "ad2024v28",
        "thumbnail" : "thumbnail.jpeg"
    },
    {
        "title": "Video 55",
        "url": "y2mate.com - KRA iTax_1080p.mp4",
        "website": "website",
        "category": "Corporate Advertising",
        "likes": 0,
        "views": 0,
        "WatchHours" : 0,
        "videoId" : "ad2024c29",
        "thumbnail" : "thumbnail.jpeg"
    },
    {
        "title": "Video 56",
        "url": "y2mate.com - Royco Cubes  For The Tastiest Beans CrumbleCrumble_1080p.mp4",
        "website": "website",
        "category": "Public Service Advertising (PSA)",
        "likes": 0,
        "views": 0,
        "WatchHours" : 0,
        "videoId" : "ad2024v30",
        "thumbnail" : "thumbnail.jpeg"
    },
    {
        "title": "Video 57",
        "url": "y2mate.com - Juicy Fruit Flavors 2_480p.mp4",
        "website": "website",
        "category": "Retail Advertising",
        "likes": 0,
        "views": 0,
        "WatchHours" : 0,
        "videoId" : "ad2024v31",
        "thumbnail" : "thumbnail.jpeg"
    },
    {
        "title": "Video 58",
        "url": "adnewone.mp4",
        "website": "website",
        "category": "B2B Advertising",
        "likes": 0,
        "views": 0,
        "WatchHours" : 0,
        "videoId" : "ad2024v32",
        "thumbnail" : "thumbnail.jpeg"
    },
    {
        "title": "Video 59",
        "url": "y2mate.com - Get 1 GB  50 BOB Valid for 24hrs only Available on Airtel Money_1080p.mp4",
        "website": "website",
        "category": "Celebrity Endorsements",
        "likes": 0,
        "views": 0,
        "videoId" : "ad2024v33",
        "thumbnail"  : "thumbnail.jpeg"
    },
    {
        "title": "Video 60",
        "url": "y2mate.com - Hotbots Kia Cerato Big Game Car Ad_1080p.mp4",
        "website": "website",
        "category": "Event Sponsorship",
        "likes": 0,
        "views": 0,
        "videoId" : "ad2024v34",
        "thumbnail" : "thumbnail.jpeg"
    },
    {
        "title": "Video 61",
        "url": "y2mate.com - KISS Condom Ad Ghana 2015_480p.mp4",
        "website": "website",
        "category": "Corporate Advertising",
        "likes": 0,
        "views": 0,
        "WatchHours" : 0,
        "videoId" : "ad2024v35",
        "thumbnail" : "thumbnail.jpeg"
    },
    {
        "title": "Video 62",
        "url": "y2mate.com - Save data with Opera Mini browser_1080p.mp4",
        "website": "website",
        "category": "Product Advertising",
        "likes": 0,
        "views": 0,
        "videoId" : "ad2024v36",
        "thumbnail" : "thumbnail.jpeg"
    },
    {
        "title": "Video 63",
        "url": "y2mate.com - Experience the new look of Microsoft Edge_1080p.mp4",
        "website": "website",
        "category": "Brand Advertising",
        "likes": 0,
        "views": 0,
        "WatchHours" : 0,
        "videoId" : "ad2024v37",
        "thumbnail" : "thumbnail.jpeg"
    }

]
